agentforce/__init__.py
agentforce/agents.py
agentforce/constant/__init__.py
agentforce/constant/constants.py
agentforce/data/__init__.py
agentforce/data/end_session.py
agentforce/data/message.py
agentforce/data/session.py
agentforce/rest/__init__.py
agentforce/rest/authenticate.py
agentforce/rest/end_session.py
agentforce/rest/send_message.py
agentforce/rest/start_session.py
salesforce_agentforce-0.1.9.dist-info/LICENSE
salesforce_agentforce-0.1.9.dist-info/METADATA
salesforce_agentforce-0.1.9.dist-info/WHEEL
salesforce_agentforce-0.1.9.dist-info/top_level.txt
salesforce_agentforce-0.1.9.dist-info/RECORD
