Metadata-Version: 2.1
Name: salesforce-agentforce
Version: 0.1.9
Summary: A Python SDK for interacting with the Agentforce Agents
Home-page: https://github.com/amirkhan-ak-sf/agentforce
Author: Amir Khan
Author-email: amir.khan@salesforce.com
License: UNKNOWN
Platform: UNKNOWN
Classifier: Development Status :: 4 - Beta
Classifier: Intended Audience :: Developers
Classifier: License :: OSI Approved :: MIT License
Classifier: Operating System :: OS Independent
Classifier: Programming Language :: Python :: 3
Classifier: Programming Language :: Python :: 3.7
Classifier: Programming Language :: Python :: 3.8
Classifier: Programming Language :: Python :: 3.9
Classifier: Programming Language :: Python :: 3.10
Requires-Python: >=3.7
Requires-Dist: requests (>=2.25.0)
